barky/__init__.py
barky/barky.py
Barky-1.0.1.dist-info/LICENSE
Barky-1.0.1.dist-info/METADATA
Barky-1.0.1.dist-info/WHEEL
Barky-1.0.1.dist-info/entry_points.txt
Barky-1.0.1.dist-info/top_level.txt
Barky-1.0.1.dist-info/zip-safe
Barky-1.0.1.dist-info/RECORD
