Metadata-Version: 2.1
Name: Barky
Version: 1.0.1
Summary: Push notifications to your iPhone with Bark.
Home-page: https://github.com/well-shark/Barky
Author: WellShark
Author-email: wellshark.net@gmail.com
License: MIT
Keywords: Bark,Push,Notification,iPhone,iOS
Platform: UNKNOWN
Classifier: Development Status :: 1 - Planning
Classifier: Programming Language :: Python :: 3
Classifier: License :: OSI Approved :: MIT License
Classifier: Operating System :: OS Independent
Requires-Python: >=3.4.0
License-File: LICENSE
